{
  "questions": [
    {
      "question": "What is book keeping?",
      "options": [
        "A) Bookkeeping is the organized process of tracking all income and expense transactions.",
        "B) Bookkeeping is the art of selling your product",
        "C) Bookkeeping is the process of manufacturing products"
      ],
      "answer": "a"
    },
    {
      "question": "The money withdraw by the owner for personal use is called…",
      "options": [
        "A) acting",
        "B) drawings",
        "C) Singing"
      ],
      "answer": "b"
    },
    {
      "question": "What are the purpose of bookkeeping for record purpose?",
      "options": [
        "A) Informed business decision making",
        "B) Securing loans and grants",
        "C) All of the above"
      ],
      "answer": "c"
    },
    {
      "question": "Which of the following are reasons for good financial management? Select all that apply.",
      "options": [
        "A) Helps to show which products or services are profitable",
        "B) Provides information on the size of a loan a business can afford",
        "C) All of the above"
      ],
      "answer": "c"
    },
    {
      "question": "New businesses should start financial management with a(n) _______________________?",
      "options": [
        "A) Business credit card",
        "B) Budget",
        "C) Inventory purchase"
      ],
      "answer": "b"
    }
  ]
}
